LICENSE
MANIFEST.in
README.md
pyproject.toml
setup.py
MRArbDcf.egg-info/PKG-INFO
MRArbDcf.egg-info/SOURCES.txt
MRArbDcf.egg-info/dependency_links.txt
MRArbDcf.egg-info/requires.txt
MRArbDcf.egg-info/top_level.txt
dev/benchmark.py
dev/plot.py
dev/psearch.py
dev/recon_phantom.py
dev/recon_phantom_sos.py
dev/test_finufft3d1.py
dev/test_finufft3d2.py
dev/pipedcf/Function.py
dev/pipedcf/Type.py
dev/pipedcf/Utility.py
dev/pipedcf/__init__.py
dev/slime/Function.py
dev/slime/Type.py
dev/slime/Utility.py
dev/slime/__init__.py
example/example_3d.py
mrarbdcf_src/Function.py
mrarbdcf_src/Utility.py
mrarbdcf_src/__init__.py