Metadata-Version: 2.4
Name: MRArbDcf
Version: 1.0.6
Summary: Density Compensation Function Design Tool for Arbirary k-Space Trajectoryies.
Author-email: Ryan <ryan_shanghaitech@proton.me>
License-Expression: MIT
Project-URL: Repository, https://github.com/RyanShanghaitech/MRArbDcf
Project-URL: Examples, https://github.com/RyanShanghaitech/MRArbDcf/tree/main/example
Keywords: MRI,non-Cartesian,Reconstruction,DCF,Density-Compensation
License-File: LICENSE
Requires-Dist: numpy
Requires-Dist: finufft
Requires-Dist: psutil
Dynamic: license-file
